search4/__init__.py
search4/search4.py
search4/search4.yml
search4/utils.py
search4-2.3.0.dist-info/entry_points.txt
search4-2.3.0.dist-info/LICENSE
search4-2.3.0.dist-info/WHEEL
search4-2.3.0.dist-info/METADATA
search4-2.3.0.dist-info/RECORD
