Metadata-Version: 2.1
Name: search4
Version: 2.3.0
Summary: Sweet OSINT tool to find people on the social media.
Author: anil chauhan
Author-email: anilchauhanxda@gmail.com
Requires-Python: >=3.7,<4.0
Classifier: Programming Language :: Python :: 3
Classifier: Programming Language :: Python :: 3.10
Classifier: Programming Language :: Python :: 3.7
Classifier: Programming Language :: Python :: 3.8
Classifier: Programming Language :: Python :: 3.9
Requires-Dist: Jinja2 (>=3.1.2,<4.0.0)
Requires-Dist: PyYAML (>=6.0,<7.0)
Requires-Dist: colorama (>=0.4.5,<0.5.0)
Requires-Dist: requests (>=2.28.1,<3.0.0)
